fft_multiplication/__init__.py
fft_multiplication/fft_multiplication.py
fft_multiplication-0.0.2.dist-info/METADATA
fft_multiplication-0.0.2.dist-info/WHEEL
fft_multiplication-0.0.2.dist-info/licenses/LICENSE
fft_multiplication-0.0.2.dist-info/RECORD
