Metadata-Version: 2.1
Name: fft_multiplication
Version: 0.0.2
Summary: FFT Multiplication
Project-URL: Homepage, https://github.com/mo-inkhan/FFT-Multiplication
Project-URL: Bug Tracker, https://github.com/mo-inkhan/FFT-Multiplication/issues
Project-URL: Source, https://github.com/mo-inkhan/FFT-Multiplication
Author-email: Moin Khan <mo.inkhan@aol.com>
License-File: LICENSE
Keywords: FFT,FFT Multiplication
Classifier: License :: OSI Approved :: MIT License
Classifier: Operating System :: OS Independent
Classifier: Programming Language :: Python :: 3
Requires-Python: >=3.7
